MANIFEST.in
README.rst
setup.cfg
setup.py
docs/CONTRIBUTORS.rst
docs/HISTORY.rst
docs/INSTALL.txt
docs/LICENSE.GPL
docs/LICENSE.txt
seantis/__init__.py
seantis.dir.events.egg-info/PKG-INFO
seantis.dir.events.egg-info/SOURCES.txt
seantis.dir.events.egg-info/dependency_links.txt
seantis.dir.events.egg-info/entry_points.txt
seantis.dir.events.egg-info/namespace_packages.txt
seantis.dir.events.egg-info/not-zip-safe
seantis.dir.events.egg-info/requires.txt
seantis.dir.events.egg-info/top_level.txt
seantis/dir/__init__.py
seantis/dir/events/__init__.py
seantis/dir/events/catalog.py
seantis/dir/events/cleanup.py
seantis/dir/events/conditions.py
seantis/dir/events/configure.zcml
seantis/dir/events/dates.py
seantis/dir/events/directory.py
seantis/dir/events/form.py
seantis/dir/events/interfaces.py
seantis/dir/events/item.py
seantis/dir/events/macros.py
seantis/dir/events/maintenance.py
seantis/dir/events/recurrence.py
seantis/dir/events/setuphandler.py
seantis/dir/events/submission.py
seantis/dir/events/sync.sh
seantis/dir/events/token.py
seantis/dir/events/upgrades.py
seantis/dir/events/upgrades.zcml
seantis/dir/events/utils.py
seantis/dir/events/css/base.css
seantis/dir/events/css/recurrence.css
seantis/dir/events/css/izug/directory.css
seantis/dir/events/css/izug/ie10fixes.css
seantis/dir/events/css/izug/ie8fixes.css
seantis/dir/events/css/izug/ie9fixes.css
seantis/dir/events/css/sunburst/directory.css
seantis/dir/events/css/teamraum/directory.css
seantis/dir/events/js/counter.js
seantis/dir/events/js/daterange.js
seantis/dir/events/js/dependencies.js
seantis/dir/events/js/filter.js
seantis/dir/events/js/form.js
seantis/dir/events/js/overlay.js
seantis/dir/events/locales/seantis.dir.events.pot
seantis/dir/events/locales/de/LC_MESSAGES/plone.po
seantis/dir/events/locales/de/LC_MESSAGES/seantis.dir.events.po
seantis/dir/events/profiles/default/catalog.xml
seantis/dir/events/profiles/default/cssregistry.xml
seantis/dir/events/profiles/default/jsregistry.xml
seantis/dir/events/profiles/default/metadata.xml
seantis/dir/events/profiles/default/rolemap.xml
seantis/dir/events/profiles/default/seantis.dir.events-default.txt
seantis/dir/events/profiles/default/types.xml
seantis/dir/events/profiles/default/workflows.xml
seantis/dir/events/profiles/default/types/seantis.dir.events.directory.xml
