Metadata-Version: 1.1
Name: seantis.dir.events
Version: 1.9
Summary: Directory of upcoming Events.
Home-page: https://github.com/seantis/seantis.dir.events
Author: Seantis GmbH
Author-email: info@seantis.ch
License: GPL
Platform: UNKNOWN
Classifier: Framework :: Plone
Classifier: Programming Language :: Python
